[
  {
    "Author": "XSZYYS",
    "Name": "XSZToolbox",
    "InternalName": "XSZToolbox",
    "AssemblyVersion": "1.5.8.4",
    "Description": "小小工具箱",
    "ApplicableVersion": "any",
    "RepoUrl": "https://github.com/ShoOtaku/DalamudPlugins",
    "Tags": [
      "utility"
    ],
    "CategoryTags": [
      "utility"
    ],
    "DalamudApiLevel": 14,
    "IconUrl": "https://raw.githubusercontent.com/ShoOtaku/DalamudPlugins/main/plugins/XSZToolbox/icon.png",
    "Punchline": "小小工具箱",
    "AcceptsFeedback": true,
    "DownloadLinkInstall": "https://raw.githubusercontent.com/ShoOtaku/DalamudPlugins/main/plugins/XSZToolbox/latest.zip",
    "DownloadLinkTesting": "https://raw.githubusercontent.com/ShoOtaku/DalamudPlugins/main/plugins/XSZToolbox/latest.zip",
    "DownloadLinkUpdate": "https://raw.githubusercontent.com/ShoOtaku/DalamudPlugins/main/plugins/XSZToolbox/latest.zip",
    "DownloadCount": 0,
    "LastUpdate": 1769927076,
    "Changelog": "新增discord频道，现在可以bot验证了；修改了使用能源包的方式，现在能更稳定。"
  }
]